major/__init__.py
major-0.0.1.dist-info/DESCRIPTION.rst
major-0.0.1.dist-info/METADATA
major-0.0.1.dist-info/RECORD
major-0.0.1.dist-info/WHEEL
major-0.0.1.dist-info/metadata.json
major-0.0.1.dist-info/top_level.txt
